quicksort/__init__.py
quicksort/quicksort.py
QuickSort_Implementation-0.0.1.dist-info/LICENSE
QuickSort_Implementation-0.0.1.dist-info/METADATA
QuickSort_Implementation-0.0.1.dist-info/WHEEL
QuickSort_Implementation-0.0.1.dist-info/top_level.txt
QuickSort_Implementation-0.0.1.dist-info/RECORD
