Metadata-Version: 2.1
Name: QuickSort-Implementation
Version: 0.0.1
Summary: Sorting a list of numbers with quicksort
Home-page: UNKNOWN
Author: Shashank Saurav
Author-email: UNKNOWN
License: MIT
Platform: UNKNOWN
